CHANGES.rst
MANIFEST.in
README.rst
setup.cfg
setup.py
collective/__init__.py
collective.sortmyfolder.egg-info/PKG-INFO
collective.sortmyfolder.egg-info/SOURCES.txt
collective.sortmyfolder.egg-info/dependency_links.txt
collective.sortmyfolder.egg-info/entry_points.txt
collective.sortmyfolder.egg-info/namespace_packages.txt
collective.sortmyfolder.egg-info/not-zip-safe
collective.sortmyfolder.egg-info/requires.txt
collective.sortmyfolder.egg-info/top_level.txt
collective/sortmyfolder/__init__.py
collective/sortmyfolder/configure.zcml
collective/sortmyfolder/i18n.sh
collective/sortmyfolder/migration.py
collective/sortmyfolder/tests.py
collective/sortmyfolder/Extensions/install.py
collective/sortmyfolder/browser/__init__.py
collective/sortmyfolder/browser/configure.zcml
collective/sortmyfolder/browser/sort-icon.png
collective/sortmyfolder/browser/sort_contents.pt
collective/sortmyfolder/browser/sort_contents.py
collective/sortmyfolder/browser/sortmyfolder.js
collective/sortmyfolder/locales/collective.sortmyfolder-manual.pot
collective/sortmyfolder/locales/collective.sortmyfolder.pot
collective/sortmyfolder/locales/it/LC_MESSAGES/collective.sortmyfolder.mo
collective/sortmyfolder/locales/it/LC_MESSAGES/collective.sortmyfolder.po
collective/sortmyfolder/locales/nl/LC_MESSAGES/collective.sortmyfolder.mo
collective/sortmyfolder/locales/nl/LC_MESSAGES/collective.sortmyfolder.po
collective/sortmyfolder/profiles/default/actionicons.xml
collective/sortmyfolder/profiles/default/actions.xml
collective/sortmyfolder/profiles/default/metadata.xml
collective/sortmyfolder/profiles/default/skins.xml
collective/sortmyfolder/profiles/uninstall/skins.xml
collective/sortmyfolder/skins/sortmyfolder/folder_position.cpy
collective/sortmyfolder/skins/sortmyfolder/folder_position.cpy.metadata
docs/INSTALL.txt
docs/LICENSE.GPL
docs/LICENSE.txt